meidengtest/__init__.py
meidengtest/cli.py
meidengtest/meidengtest.py
meidengtest-0.1.0.dist-info/AUTHORS.rst
meidengtest-0.1.0.dist-info/LICENSE
meidengtest-0.1.0.dist-info/METADATA
meidengtest-0.1.0.dist-info/WHEEL
meidengtest-0.1.0.dist-info/entry_points.txt
meidengtest-0.1.0.dist-info/top_level.txt
meidengtest-0.1.0.dist-info/RECORD
